mestr/__init__.py
mestr/mestr.py
mestr-1.0.6.dist-info/DESCRIPTION.rst
mestr-1.0.6.dist-info/METADATA
mestr-1.0.6.dist-info/RECORD
mestr-1.0.6.dist-info/WHEEL
mestr-1.0.6.dist-info/metadata.json
mestr-1.0.6.dist-info/top_level.txt
