Metadata-Version: 2.0
Name: mestr
Version: 1.0.6
Summary: Bring dynamic component registration to wamp crossbar router.
Home-page: https://github.com/Scille/mestr
Author: Scille SAS
Author-email: contact@scille.fr
License: ISCL
Keywords: mestr
Platform: UNKNOWN
Classifier: Development Status :: 2 - Pre-Alpha
Classifier: Intended Audience :: Developers
Classifier: License :: OSI Approved :: ISC License (ISCL)
Classifier: Natural Language :: English
Classifier: Programming Language :: Python :: 2
Classifier: Programming Language :: Python :: 2.6
Classifier: Programming Language :: Python :: 2.7
Classifier: Programming Language :: Python :: 3
Classifier: Programming Language :: Python :: 3.3
Classifier: Programming Language :: Python :: 3.4
Classifier: Programming Language :: Python :: 3.5
